nnabla/__init__.py
nnabla/__main__.py
nnabla/_arithmetic_ops.cp39-win_amd64.pyd
nnabla/_array.cp39-win_amd64.pyd
nnabla/_computation_graph.cp39-win_amd64.pyd
nnabla/_dropout_workaround.cp39-win_amd64.pyd
nnabla/_indexing.cp39-win_amd64.pyd
nnabla/_init.cp39-win_amd64.pyd
nnabla/_nd_array.cp39-win_amd64.pyd
nnabla/_variable.cp39-win_amd64.pyd
nnabla/_version.py
nnabla/archive.lib
nnabla/archive_static.lib
nnabla/auto_forward.cp39-win_amd64.pyd
nnabla/autolog.py
nnabla/backward_functions.py
nnabla/callback.cp39-win_amd64.pyd
nnabla/communicator.cp39-win_amd64.pyd
nnabla/communicators.py
nnabla/config.py
nnabla/context.py
nnabla/dtypes.py
nnabla/ext_utils.py
nnabla/filter_plugin1_dsets.lib
nnabla/filter_plugin2_dsets.lib
nnabla/filter_plugin3_dsets.lib
nnabla/filter_plugin4_groups.lib
nnabla/function.cp39-win_amd64.pyd
nnabla/function_bases.py
nnabla/functions.py
nnabla/grad.py
nnabla/hdf5.lib
nnabla/hdf5_hl.lib
nnabla/hdf5_test.lib
nnabla/initializer.py
nnabla/libprotobuf-lite.lib
nnabla/libprotobuf.lib
nnabla/libprotoc.lib
nnabla/lms.cp39-win_amd64.pyd
nnabla/logger.py
nnabla/mlflow_save_load_model.py
nnabla/monitor.py
nnabla/nnabla.conf
nnabla/nnabla.dll
nnabla/nnabla.lib
nnabla/nnabla_cli.lib
nnabla/nnabla_utils.lib
nnabla/normalization_functions.py
nnabla/null_vol_connector.lib
nnabla/numpy_compat_functions.py
nnabla/parameter.py
nnabla/parametric_functions.py
nnabla/random.cp39-win_amd64.pyd
nnabla/recompute.cp39-win_amd64.pyd
nnabla/solver.cp39-win_amd64.pyd
nnabla/solvers.py
nnabla/variable.py
nnabla/zlibstat.lib
nnabla/zlibwapi.lib
nnabla/backward_function/abs.py
nnabla/backward_function/absolute_error.py
nnabla/backward_function/acos.py
nnabla/backward_function/acosh.py
nnabla/backward_function/adaptive_separable_convolution.py
nnabla/backward_function/add2.py
nnabla/backward_function/add_n.py
nnabla/backward_function/add_scalar.py
nnabla/backward_function/affine.py
nnabla/backward_function/affine_grid.py
nnabla/backward_function/arange.py
nnabla-1.39.0.dist-info/METADATA
nnabla-1.39.0.dist-info/WHEEL
nnabla-1.39.0.dist-info/entry_points.txt
nnabla-1.39.0.dist-info/top_level.txt
nnabla-1.39.0.dist-info/RECORD
