Metadata-Version: 2.1
Name: nnabla
Version: 1.39.0
Summary: Neural Network Libraries
Home-page: https://github.com/sony/nnabla
Author: Takuya Narihira, Sony Corporation
Author-email: nnabla@googlegroups.com
License: Apache License 2.0
Keywords: deep learning artificial intelligence machine learning neural network
Classifier: Development Status :: 5 - Production/Stable
Classifier: Intended Audience :: Developers
Classifier: Intended Audience :: Education
Classifier: Intended Audience :: Science/Research
Classifier: Topic :: Scientific/Engineering
Classifier: Topic :: Scientific/Engineering :: Artificial Intelligence
Classifier: License :: OSI Approved :: Apache Software License
Classifier: Programming Language :: C++
Classifier: Programming Language :: Python :: 3
Classifier: Programming Language :: Python :: 3.8
Classifier: Programming Language :: Python :: 3.9
Classifier: Programming Language :: Python :: 3.10
Classifier: Programming Language :: Python :: Implementation :: CPython
Classifier: Operating System :: Microsoft :: Windows
Classifier: Operating System :: POSIX :: Linux
Classifier: Operating System :: MacOS :: MacOS X
Requires-Python: >=3.5
Requires-Dist: setuptools
Requires-Dist: Cython
Requires-Dist: numpy ~=1.26.0
Requires-Dist: boto3
Requires-Dist: configparser
Requires-Dist: contextlib2
Requires-Dist: h5py
Requires-Dist: protobuf ~=3.20
Requires-Dist: pyyaml
Requires-Dist: scipy
Requires-Dist: six
Requires-Dist: tqdm
Requires-Dist: imageio
Requires-Dist: pillow >=9.1.0
Requires-Dist: ply
Requires-Dist: certifi
Requires-Dist: pywin32
